SSL_Interface/__init__.py
SSL_Interface/configs/__init__.py
SSL_Interface/configs/baseConfig.py
SSL_Interface/configs/interfaceConfig.py
SSL_Interface/interfaces/__init__.py
SSL_Interface/interfaces/baseInterface.py
SSL_Interface/interfaces/hconvInterface.py
SSL_Interface/interfaces/weightedSumInterface.py
SSL_Interface-0.1.0.dist-info/LICENSE
SSL_Interface-0.1.0.dist-info/METADATA
SSL_Interface-0.1.0.dist-info/WHEEL
SSL_Interface-0.1.0.dist-info/top_level.txt
SSL_Interface-0.1.0.dist-info/RECORD
