Metadata-Version: 2.1
Name: SSL_Interface
Version: 0.1.0
Summary: Interface module for Self-supervised Speech Models
Home-page: https://github.com/atosystem/SSL_Interface
Author: Yi-Jen Shih
Author-email: yjshih@utexas.edu
License: BSD license
License-File: LICENSE
Requires-Dist: numpy
Requires-Dist: torch
